glisten/Logger.py
glisten/__init__.py
glisten-1.0.2.dist-info/LICENSE
glisten-1.0.2.dist-info/METADATA
glisten-1.0.2.dist-info/WHEEL
glisten-1.0.2.dist-info/top_level.txt
glisten-1.0.2.dist-info/RECORD
