Metadata-Version: 2.1
Name: glisten
Version: 1.0.2
Summary: A simple python logging library.
Author: Sean Richards
Author-email: ordinarystarman@gmail.com
License: MIT License
Project-URL: Source, https://github.com/krytic/glisten
Project-URL: Bug Tracker, https://github.com/krytic/glisten/issues
Requires-Python: >=3
License-File: LICENSE
Requires-Dist: colorama
Requires-Dist: tqdm
